Workbook

Sheet Customers
A1: Customer Totals - Top 10 Highlighted
A2: Green = Top 10 customers by Total Purchase (Conditional Formatting > Top/Bottom Rules > Top 10 Items). Customers are grouped by Customer_ID.
A3: High-value threshold: | C3: 8300 | D3: <- change me (assumption: about the top 25% of customers)
A4: Customer_ID | B4: Orders | C4: Total Purchase | D4: Total Profit | E4: Profit Margin | F4: Rank | G4: Unique Rank | H4: Tier
A5: CUST001 | B5: =COUNTIF(Data!$A$2:$A$201,A5) -> 7 | C5: =SUMIFS(Data!$E$2:$E$201,Data!$A$2:$A$201,A5) -> 6549.55 | D5: =SUMIFS(Data!$I$2:$I$201,Data!$A$2:$A$201,A5) -> 1868.77 | E5: =IF(C5=0,0,D5/C5) -> 0.285328 | F5: =RANK(C5,$C$5:$C$34) -> 15 | G5: =F5+COUNTIF($F$5:F5,F5)-1 -> 15 | H5: =IF(C5>=$C$3,"High Value","Standard") -> Standard
A6: CUST002 | B6: =COUNTIF(Data!$A$2:$A$201,A6) -> 6 | C6: =SUMIFS(Data!$E$2:$E$201,Data!$A$2:$A$201,A6) -> 6481.43 | D6: =SUMIFS(Data!$I$2:$I$201,Data!$A$2:$A$201,A6) -> 2210.74 | E6: =IF(C6=0,0,D6/C6) -> 0.34108831 | F6: =RANK(C6,$C$5:$C$34) -> 17 | G6: =F6+COUNTIF($F$5:F6,F6)-1 -> 17 | H6: =IF(C6>=$C$3,"High Value","Standard") -> Standard
A7: CUST003 | B7: =COUNTIF(Data!$A$2:$A$201,A7) -> 9 | C7: =SUMIFS(Data!$E$2:$E$201,Data!$A$2:$A$201,A7) -> 8490.18 | D7: =SUMIFS(Data!$I$2:$I$201,Data!$A$2:$A$201,A7) -> 2652.75 | E7: =IF(C7=0,0,D7/C7) -> 0.31244921 | F7: =RANK(C7,$C$5:$C$34) -> 7 | G7: =F7+COUNTIF($F$5:F7,F7)-1 -> 7 | H7: =IF(C7>=$C$3,"High Value","Standard") -> High Value
A8: CUST004 | B8: =COUNTIF(Data!$A$2:$A$201,A8) -> 7 | C8: =SUMIFS(Data!$E$2:$E$201,Data!$A$2:$A$201,A8) -> 7813.59 | D8: =SUMIFS(Data!$I$2:$I$201,Data!$A$2:$A$201,A8) -> 3211.82 | E8: =IF(C8=0,0,D8/C8) -> 0.41105561 | F8: =RANK(C8,$C$5:$C$34) -> 10 | G8: =F8+COUNTIF($F$5:F8,F8)-1 -> 10 | H8: =IF(C8>=$C$3,"High Value","Standard") -> Standard
A9: CUST005 | B9: =COUNTIF(Data!$A$2:$A$201,A9) -> 6 | C9: =SUMIFS(Data!$E$2:$E$201,Data!$A$2:$A$201,A9) -> 6666.13 | D9: =SUMIFS(Data!$I$2:$I$201,Data!$A$2:$A$201,A9) -> 1982.39 | E9: =IF(C9=0,0,D9/C9) -> 0.29738244 | F9: =RANK(C9,$C$5:$C$34) -> 14 | G9: =F9+COUNTIF($F$5:F9,F9)-1 -> 14 | H9: =IF(C9>=$C$3,"High Value","Standard") -> Standard
A10: CUST006 | B10: =COUNTIF(Data!$A$2:$A$201,A10) -> 2 | C10: =SUMIFS(Data!$E$2:$E$201,Data!$A$2:$A$201,A10) -> 2699.75 | D10: =SUMIFS(Data!$I$2:$I$201,Data!$A$2:$A$201,A10) -> 837.06 | E10: =IF(C10=0,0,D10/C10) -> 0.31005093 | F10: =RANK(C10,$C$5:$C$34) -> 30 | G10: =F10+COUNTIF($F$5:F10,F10)-1 -> 30 | H10: =IF(C10>=$C$3,"High Value","Standard") -> Standard
A11: CUST007 | B11: =COUNTIF(Data!$A$2:$A$201,A11) -> 10 | C11: =SUMIFS(Data!$E$2:$E$201,Data!$A$2:$A$201,A11) -> 9941.88 | D11: =SUMIFS(Data!$I$2:$I$201,Data!$A$2:$A$201,A11) -> 3936.26 | E11: =IF(C11=0,0,D11/C11) -> 0.39592713 | F11: =RANK(C11,$C$5:$C$34) -> 3 | G11: =F11+COUNTIF($F$5:F11,F11)-1 -> 3 | H11: =IF(C11>=$C$3,"High Value","Standard") -> High Value
A12: CUST008 | B12: =COUNTIF(Data!$A$2:$A$201,A12) -> 10 | C12: =SUMIFS(Data!$E$2:$E$201,Data!$A$2:$A$201,A12) -> 9760.8 | D12: =SUMIFS(Data!$I$2:$I$201,Data!$A$2:$A$201,A12) -> 3442.48 | E12: =IF(C12=0,0,D12/C12) -> 0.35268421 | F12: =RANK(C12,$C$5:$C$34) -> 4 | G12: =F12+COUNTIF($F$5:F12,F12)-1 -> 4 | H12: =IF(C12>=$C$3,"High Value","Standard") -> High Value
A13: CUST009 | B13: =COUNTIF(Data!$A$2:$A$201,A13) -> 7 | C13: =SUMIFS(Data!$E$2:$E$201,Data!$A$2:$A$201,A13) -> 6505.2 | D13: =SUMIFS(Data!$I$2:$I$201,Data!$A$2:$A$201,A13) -> 2052.54 | E13: =IF(C13=0,0,D13/C13) -> 0.31552297 | F13: =RANK(C13,$C$5:$C$34) -> 16 | G13: =F13+COUNTIF($F$5:F13,F13)-1 -> 16 | H13: =IF(C13>=$C$3,"High Value","Standard") -> Standard
A14: CUST010 | B14: =COUNTIF(Data!$A$2:$A$201,A14) -> 5 | C14: =SUMIFS(Data!$E$2:$E$201,Data!$A$2:$A$201,A14) -> 4259.22 | D14: =SUMIFS(Data!$I$2:$I$201,Data!$A$2:$A$201,A14) -> 1529.32 | E14: =IF(C14=0,0,D14/C14) -> 0.35906105 | F14: =RANK(C14,$C$5:$C$34) -> 24 | G14: =F14+COUNTIF($F$5:F14,F14)-1 -> 24 | H14: =IF(C14>=$C$3,"High Value","Standard") -> Standard
A15: CUST011 | B15: =COUNTIF(Data!$A$2:$A$201,A15) -> 4 | C15: =SUMIFS(Data!$E$2:$E$201,Data!$A$2:$A$201,A15) -> 3762.29 | D15: =SUMIFS(Data!$I$2:$I$201,Data!$A$2:$A$201,A15) -> 1545.04 | E15: =IF(C15=0,0,D15/C15) -> 0.41066478 | F15: =RANK(C15,$C$5:$C$34) -> 27 | G15: =F15+COUNTIF($F$5:F15,F15)-1 -> 27 | H15: =IF(C15>=$C$3,"High Value","Standard") -> Standard
A16: CUST012 | B16: =COUNTIF(Data!$A$2:$A$201,A16) -> 9 | C16: =SUMIFS(Data!$E$2:$E$201,Data!$A$2:$A$201,A16) -> 8339 | D16: =SUMIFS(Data!$I$2:$I$201,Data!$A$2:$A$201,A16) -> 2988.71 | E16: =IF(C16=0,0,D16/C16) -> 0.35840149 | F16: =RANK(C16,$C$5:$C$34) -> 8 | G16: =F16+COUNTIF($F$5:F16,F16)-1 -> 8 | H16: =IF(C16>=$C$3,"High Value","Standard") -> High Value
... A34: CUST030 | B34: =COUNTIF(Data!$A$2:$A$201,A34) -> 9 | C34: =SUMIFS(Data!$E$2:$E$201,Data!$A$2:$A$201,A34) -> 7928.71 | D34: =SUMIFS(Data!$I$2:$I$201,Data!$A$2:$A$201,A34) -> 2965.48 | E34: =IF(C34=0,0,D34/C34) -> 0.37401797 | F34: =RANK(C34,$C$5:$C$34) -> 9 | G34: =F34+COUNTIF($F$5:F34,F34)-1 -> 9 | H34: =IF(C34>=$C$3,"High Value","Standard") -> Standard

Sheet What-If
A1: What-If Analysis - Discount vs Total Profit
A2: Change the yellow cells. Profit = (Gross Sales x (1 - Discount) - Cost) x (1 + Volume change). Sales in your data is treated as net of discount.
A4: Gross Sales (before discount) | B4: =SUM(Data!$J$2:$J$201) -> 218027.19
A5: Total Cost | B5: =SUM(Data!$K$2:$K$201) -> 126930.75
A6: Current weighted discount | B6: =1-SUM(Data!$E$2:$E$201)/SUM(Data!$J$2:$J$201) -> 0.10461738
A7: Current Total Profit | B7: =SUM(Data!$I$2:$I$201) -> 68287.01
A9: INPUTS
A10: New discount rate | B10: 0.1
A11: Volume elasticity (extra volume % per 1 pt of discount) | B11: 2 | C11: Assumption (not from data): 2.0 means a 1-pt discount lifts volume 2%.
A13: RESULT
A14: Volume change | B14: =B11*(B10-B6) -> -0.0092347616
A15: Scenario Total Profit | B15: =(B4*(1-B10)-B5)*(1+B14) -> 68653.814
A16: Change vs current profit | B16: =B15-B7 -> 366.80355
A17: % change in profit | B17: =IF(B7=0,0,B16/B7) -> 0.0053714982
A19: ONE-WAY TABLE: Discount rate -> Profit (uses elasticity in B11) | F19: TWO-WAY TABLE: Discount (rows) x Elasticity (columns) -> Profit
A20: Discount rate | B20: Volume change | C20: Total Profit | D20: Change vs current | F20: Disc \ Elast | G20: 0 | H20: 1 | I20: 2 | J20: 3 | K20: 4
A21: 0 | B21: =$B$11*(A21-$B$6) -> -0.20923476 | C21: =($B$4*(1-A21)-$B$5)*(1+B21) -> 72035.901 | D21: =C21-$B$7 -> 3748.8912 | F21: 0 | G21: =($B$4*(1-$F21)-$B$5)*(1+G$20*($F21-$B$6)) -> 91096.444 | H21: =($B$4*(1-$F21)-$B$5)*(1+H$20*($F21-$B$6)) -> 81566.173 | I21: =($B$4*(1-$F21)-$B$5)*(1+I$20*($F21-$B$6)) -> 72035.901 | J21: =($B$4*(1-$F21)-$B$5)*(1+J$20*($F21-$B$6)) -> 62505.63 | K21: =($B$4*(1-$F21)-$B$5)*(1+K$20*($F21-$B$6)) -> 52975.358
A22: 0.025 | B22: =$B$11*(A22-$B$6) -> -0.15923476 | C22: =($B$4*(1-A22)-$B$5)*(1+B22) -> 72007.981 | D22: =C22-$B$7 -> 3720.9713 | F22: 0.05 | G22: =($B$4*(1-$F22)-$B$5)*(1+G$20*($F22-$B$6)) -> 80195.084 | H22: =($B$4*(1-$F22)-$B$5)*(1+H$20*($F22-$B$6)) -> 75815.039 | I22: =($B$4*(1-$F22)-$B$5)*(1+I$20*($F22-$B$6)) -> 71434.993 | J22: =($B$4*(1-$F22)-$B$5)*(1+J$20*($F22-$B$6)) -> 67054.948 | K22: =($B$4*(1-$F22)-$B$5)*(1+K$20*($F22-$B$6)) -> 62674.902
A23: 0.05 | B23: =$B$11*(A23-$B$6) -> -0.10923476 | C23: =($B$4*(1-A23)-$B$5)*(1+B23) -> 71434.993 | D23: =C23-$B$7 -> 3147.9834 | F23: 0.1 | G23: =($B$4*(1-$F23)-$B$5)*(1+G$20*($F23-$B$6)) -> 69293.725 | H23: =($B$4*(1-$F23)-$B$5)*(1+H$20*($F23-$B$6)) -> 68973.769 | I23: =($B$4*(1-$F23)-$B$5)*(1+I$20*($F23-$B$6)) -> 68653.814 | J23: =($B$4*(1-$F23)-$B$5)*(1+J$20*($F23-$B$6)) -> 68333.858 | K23: =($B$4*(1-$F23)-$B$5)*(1+K$20*($F23-$B$6)) -> 68013.903
A24: 0.075 | B24: =$B$11*(A24-$B$6) -> -0.059234762 | C24: =($B$4*(1-A24)-$B$5)*(1+B24) -> 70316.937 | D24: =C24-$B$7 -> 2029.9275 | F24: 0.15 | G24: =($B$4*(1-$F24)-$B$5)*(1+G$20*($F24-$B$6)) -> 58392.365 | H24: =($B$4*(1-$F24)-$B$5)*(1+H$20*($F24-$B$6)) -> 61042.363 | I24: =($B$4*(1-$F24)-$B$5)*(1+I$20*($F24-$B$6)) -> 63692.362 | J24: =($B$4*(1-$F24)-$B$5)*(1+J$20*($F24-$B$6)) -> 66342.36 | K24: =($B$4*(1-$F24)-$B$5)*(1+K$20*($F24-$B$6)) -> 68992.359
A25: 0.1 | B25: =$B$11*(A25-$B$6) -> -0.0092347616 | C25: =($B$4*(1-A25)-$B$5)*(1+B25) -> 68653.814 | D25: =C25-$B$7 -> 366.80355 | F25: 0.2 | G25: =($B$4*(1-$F25)-$B$5)*(1+G$20*($F25-$B$6)) -> 47491.005 | H25: =($B$4*(1-$F25)-$B$5)*(1+H$20*($F25-$B$6)) -> 52020.822 | I25: =($B$4*(1-$F25)-$B$5)*(1+I$20*($F25-$B$6)) -> 56550.638 | J25: =($B$4*(1-$F25)-$B$5)*(1+J$20*($F25-$B$6)) -> 61080.455 | K25: =($B$4*(1-$F25)-$B$5)*(1+K$20*($F25-$B$6)) -> 65610.271
A26: 0.125 | B26: =$B$11*(A26-$B$6) -> 0.040765238 | C26: =($B$4*(1-A26)-$B$5)*(1+B26) -> 66445.622 | D26: =C26-$B$7 -> -1841.3883 | F26: 0.25 | G26: =($B$4*(1-$F26)-$B$5)*(1+G$20*($F26-$B$6)) -> 36589.645 | H26: =($B$4*(1-$F26)-$B$5)*(1+H$20*($F26-$B$6)) -> 41909.144 | I26: =($B$4*(1-$F26)-$B$5)*(1+I$20*($F26-$B$6)) -> 47228.642 | J26: =($B$4*(1-$F26)-$B$5)*(1+J$20*($F26-$B$6)) -> 52548.141 | K26: =($B$4*(1-$F26)-$B$5)*(1+K$20*($F26-$B$6)) -> 57867.639
A27: 0.15 | B27: =$B$11*(A27-$B$6) -> 0.090765238 | C27: =($B$4*(1-A27)-$B$5)*(1+B27) -> 63692.362 | D27: =C27-$B$7 -> -4594.6482 | F27: 0.3 | G27: =($B$4*(1-$F27)-$B$5)*(1+G$20*($F27-$B$6)) -> 25688.286 | H27: =($B$4*(1-$F27)-$B$5)*(1+H$20*($F27-$B$6)) -> 30707.33 | I27: =($B$4*(1-$F27)-$B$5)*(1+I$20*($F27-$B$6)) -> 35726.375 | J27: =($B$4*(1-$F27)-$B$5)*(1+J$20*($F27-$B$6)) -> 40745.419 | K27: =($B$4*(1-$F27)-$B$5)*(1+K$20*($F27-$B$6)) -> 45764.464
A28: 0.175 | B28: =$B$11*(A28-$B$6) -> 0.14076524 | C28: =($B$4*(1-A28)-$B$5)*(1+B28) -> 60394.034 | D28: =C28-$B$7 -> -7892.9761
A29: 0.2 | B29: =$B$11*(A29-$B$6) -> 0.19076524 | C29: =($B$4*(1-A29)-$B$5)*(1+B29) -> 56550.638 | D29: =C29-$B$7 -> -11736.372 | F29: Excel's own tools: Data > What-If Analysis > Data Table / Goal Seek / Scenario Manager (see Notes).
A30: 0.225 | B30: =$B$11*(A30-$B$6) -> 0.24076524 | C30: =($B$4*(1-A30)-$B$5)*(1+B30) -> 52162.174 | D30: =C30-$B$7 -> -16124.836
A31: 0.25 | B31: =$B$11*(A31-$B$6) -> 0.29076524 | C31: =($B$4*(1-A31)-$B$5)*(1+B31) -> 47228.642 | D31: =C31-$B$7 -> -21058.368
A32: 0.275 | B32: =$B$11*(A32-$B$6) -> 0.34076524 | C32: =($B$4*(1-A32)-$B$5)*(1+B32) -> 41750.043 | D32: =C32-$B$7 -> -26536.967
A33: 0.3 | B33: =$B$11*(A33-$B$6) -> 0.39076524 | C33: =($B$4*(1-A33)-$B$5)*(1+B33) -> 35726.375 | D33: =C33-$B$7 -> -32560.635

Sheet Regression
A1: Linear Regression: Profit (Y) vs Sales (X)
A2: Same layout as Data Analysis ToolPak > Regression, built with live formulas. Y = Data!I (Profit), X = Data!E (Sales).
A4: Regression Statistics
A5: Multiple R | B5: =SQRT(B6) -> 0.77340306
A6: R Square | B6: =RSQ(Data!$I$2:$I$201,Data!$E$2:$E$201) -> 0.5981523
A7: Adjusted R Square | B7: =1-(1-B6)*(B9-1)/(B9-2) -> 0.59612277
A8: Standard Error | B8: =STEYX(Data!$I$2:$I$201,Data!$E$2:$E$201) -> 86.281231
A9: Observations | B9: =COUNT(Data!$E$2:$E$201) -> 200
A11: ANOVA
B12: df | C12: SS | D12: MS | E12: F | F12: Significance F
A13: Regression | B13: 1 | C13: =B6*C15 -> 2194058.2 | D13: =C13/B13 -> 2194058.2 | E13: =D13/D14 -> 294.72398 | F13: =FDIST(E13,B13,B14) -> 4.6269368e-41
A14: Residual | B14: =B9-2 -> 198 | C14: =C15-C13 -> 1474001.2 | D14: =C14/B14 -> 7444.4507
A15: Total | B15: =B9-1 -> 199 | C15: =DEVSQ(Data!$I$2:$I$201) -> 3668059.4
A17: Coefficients
B18: Coefficients | C18: Standard Error | D18: t Stat | E18: P-value | F18: Lower 95% | G18: Upper 95%
A19: Intercept | B19: =INTERCEPT(Data!$I$2:$I$201,Data!$E$2:$E$201) -> -1.0315505 | C19: =B8*SQRT(1/B9+AVERAGE(Data!$E$2:$E$201)^2/DEVSQ(Data!$E$2:$E$201)) -> 20.860617 | D19: =B19/C19 -> -0.049449663 | E19: =TDIST(ABS(D19),$B$14,2) -> 0.9606108 | F19: =B19-TINV(0.05,$B$14)*C19 -> -42.169052 | G19: =B19+TINV(0.05,$B$14)*C19 -> 40.105951
A20: Sales (X) | B20: =SLOPE(Data!$I$2:$I$201,Data!$E$2:$E$201) -> 0.35085599 | C20: =B8/SQRT(DEVSQ(Data!$E$2:$E$201)) -> 0.020437189 | D20: =B20/C20 -> 17.167527 | E20: =TDIST(ABS(D20),$B$14,2) -> 4.6269368e-41 | F20: =B20-TINV(0.05,$B$14)*C20 -> 0.3105535 | G20: =B20+TINV(0.05,$B$14)*C20 -> 0.39115848
A22: Prediction
A23: If Sales = | B23: 1000
A24: Predicted Profit = | B24: =B19+B20*B23 -> 349.82444
A26: How to read it
A27: ="Each extra 1 of Sales changes Profit by about "&TEXT(B20,"0.000")&". Sales explains "&TEXT(B6,"0%")&" of the variation in Profit." -> Each extra 1 of Sales changes Profit by about 0.351. Sales explains 60% of the variation in Profit.
A28: =IF(F13<0.05,"P-value < 0.05: the relationship is statistically significant.","P-value >= 0.05: the relationship is NOT statistically significant.") -> P-value < 0.05: the relationship is statistically significant.

Sheet Data
A1: Customer_ID | B1: Customer_Name | C1: Region | D1: Product_Category | E1: Sales | F1: Quantity | G1: Discount | H1: Order_Date | I1: Profit | J1: Gross Sales (pre-discount) | K1: Cost (Sales-Profit) | L1: Timestamp (NOW)
A2: CUST019 | B2: James Davis | C2: West | D2: Books | E2: 1036.09 | F2: 4 | G2: 0.2 | H2: 45392 | I2: 331.55 | J2: =E2/(1-G2) -> 1295.1125 | K2: =E2-I2 -> 704.54 | L2: =NOW() -> 46323.406
A3: CUST012 | B3: Robert Anderson | C3: West | D3: Clothing | E3: 1101.28 | F3: 3 | G3: 0.2 | H3: 45393 | I3: 440.51 | J3: =E3/(1-G3) -> 1376.6 | K3: =E3-I3 -> 660.77 | L3: =NOW() -> 46323.406
A4: CUST017 | B4: James Taylor | C4: East | D4: Books | E4: 713.34 | F4: 17 | G4: 0 | H4: 45396 | I4: 285.34 | J4: =E4/(1-G4) -> 713.34 | K4: =E4-I4 -> 428 | L4: =NOW() -> 46323.406
A5: CUST005 | B5: Robert Anderson | C5: South | D5: Electronics | E5: 760.93 | F5: 4 | G5: 0.15 | H5: 45396 | I5: 161.7 | J5: =E5/(1-G5) -> 895.21176 | K5: =E5-I5 -> 599.23 | L5: =NOW() -> 46323.406
A6: CUST030 | B6: James Wilson | C6: North | D6: Books | E6: 847 | F6: 12 | G6: 0.2 | H6: 45397 | I6: 271.04 | J6: =E6/(1-G6) -> 1058.75 | K6: =E6-I6 -> 575.96 | L6: =NOW() -> 46323.406
A7: CUST007 | B7: Michael Anderson | C7: North | D7: Furniture | E7: 965.64 | F7: 8 | G7: 0.1 | H7: 45398 | I7: 304.18 | J7: =E7/(1-G7) -> 1072.9333 | K7: =E7-I7 -> 661.46 | L7: =NOW() -> 46323.406
A8: CUST001 | B8: Linda Wilson | C8: West | D8: Electronics | E8: 1317.53 | F8: 12 | G8: 0.05 | H8: 45398 | I8: 312.91 | J8: =E8/(1-G8) -> 1386.8737 | K8: =E8-I8 -> 1004.62 | L8: =NOW() -> 46323.406
A9: CUST026 | B9: Mary Davis | C9: East | D9: Furniture | E9: 1074.47 | F9: 6 | G9: 0.2 | H9: 45401 | I9: 300.85 | J9: =E9/(1-G9) -> 1343.0875 | K9: =E9-I9 -> 773.62 | L9: =NOW() -> 46323.406
A10: CUST009 | B10: Linda Jackson | C10: Central | D10: Books | E10: 501.54 | F10: 11 | G10: 0.05 | H10: 45401 | I10: 190.59 | J10: =E10/(1-G10) -> 527.93684 | K10: =E10-I10 -> 310.95 | L10: =NOW() -> 46323.406
A11: CUST010 | B11: David Thomas | C11: Central | D11: Clothing | E11: 737.31 | F11: 2 | G11: 0.05 | H11: 45401 | I11: 350.22 | J11: =E11/(1-G11) -> 776.11579 | K11: =E11-I11 -> 387.09 | L11: =NOW() -> 46323.406
A12: CUST014 | B12: Emma Davis | C12: West | D12: Office Supplies | E12: 1572.82 | F12: 6 | G12: 0.05 | H12: 45402 | I12: 672.38 | J12: =E12/(1-G12) -> 1655.6 | K12: =E12-I12 -> 900.44 | L12: =NOW() -> 46323.406
A13: CUST014 | B13: David Thomas | C13: Central | D13: Books | E13: 1343.13 | F13: 14 | G13: 0.15 | H13: 45404 | I13: 456.66 | J13: =E13/(1-G13) -> 1580.1529 | K13: =E13-I13 -> 886.47 | L13: =NOW() -> 46323.406
... A201: CUST016 | B201: David Thomas | C201: South | D201: Clothing | E201: 928.32 | F201: 2 | G201: 0.05 | H201: 45754 | I201: 440.95 | J201: =E201/(1-G201) -> 977.17895 | K201: =E201-I201 -> 487.37 | L201: =NOW() -> 46323.406

Sheet Monthly Growth
A1: Monthly Sales Growth with Up/Down Arrows
A2: Arrow = IF(growth>0,"▲",IF(growth<0,"▼","▶")); the growth column also carries an Icon Set. Apr-2025 is a partial month (data ends 7 Apr).
A4: Month | B4: Sales | C4: Profit | D4: MoM Growth % | E4: Trend
A5: 45383 | B5: =SUMIFS(Data!$E$2:$E$201,Data!$H$2:$H$201,">="&A5,Data!$H$2:$H$201,"<"&EDATE(A5,1)) -> 19029.96 | C5: =SUMIFS(Data!$I$2:$I$201,Data!$H$2:$H$201,">="&A5,Data!$H$2:$H$201,"<"&EDATE(A5,1)) -> 6244.01 | D5: -
A6: =EDATE(A5,1) -> 45413 | B6: =SUMIFS(Data!$E$2:$E$201,Data!$H$2:$H$201,">="&A6,Data!$H$2:$H$201,"<"&EDATE(A6,1)) -> 18507.34 | C6: =SUMIFS(Data!$I$2:$I$201,Data!$H$2:$H$201,">="&A6,Data!$H$2:$H$201,"<"&EDATE(A6,1)) -> 6121.35 | D6: =IF(B5=0,"",(B6-B5)/B5) -> -0.027463011 | E6: =IF(D6="","",IF(D6>0,"▲",IF(D6<0,"▼","▶"))) -> ▼
A7: =EDATE(A6,1) -> 45444 | B7: =SUMIFS(Data!$E$2:$E$201,Data!$H$2:$H$201,">="&A7,Data!$H$2:$H$201,"<"&EDATE(A7,1)) -> 20187.51 | C7: =SUMIFS(Data!$I$2:$I$201,Data!$H$2:$H$201,">="&A7,Data!$H$2:$H$201,"<"&EDATE(A7,1)) -> 6918 | D7: =IF(B6=0,"",(B7-B6)/B6) -> 0.090783981 | E7: =IF(D7="","",IF(D7>0,"▲",IF(D7<0,"▼","▶"))) -> ▲
A8: =EDATE(A7,1) -> 45474 | B8: =SUMIFS(Data!$E$2:$E$201,Data!$H$2:$H$201,">="&A8,Data!$H$2:$H$201,"<"&EDATE(A8,1)) -> 11609.04 | C8: =SUMIFS(Data!$I$2:$I$201,Data!$H$2:$H$201,">="&A8,Data!$H$2:$H$201,"<"&EDATE(A8,1)) -> 3743.85 | D8: =IF(B7=0,"",(B8-B7)/B7) -> -0.42493948 | E8: =IF(D8="","",IF(D8>0,"▲",IF(D8<0,"▼","▶"))) -> ▼
A9: =EDATE(A8,1) -> 45505 | B9: =SUMIFS(Data!$E$2:$E$201,Data!$H$2:$H$201,">="&A9,Data!$H$2:$H$201,"<"&EDATE(A9,1)) -> 10091.7 | C9: =SUMIFS(Data!$I$2:$I$201,Data!$H$2:$H$201,">="&A9,Data!$H$2:$H$201,"<"&EDATE(A9,1)) -> 3302.84 | D9: =IF(B8=0,"",(B9-B8)/B8) -> -0.13070331 | E9: =IF(D9="","",IF(D9>0,"▲",IF(D9<0,"▼","▶"))) -> ▼
A10: =EDATE(A9,1) -> 45536 | B10: =SUMIFS(Data!$E$2:$E$201,Data!$H$2:$H$201,">="&A10,Data!$H$2:$H$201,"<"&EDATE(A10,1)) -> 20533.5 | C10: =SUMIFS(Data!$I$2:$I$201,Data!$H$2:$H$201,">="&A10,Data!$H$2:$H$201,"<"&EDATE(A10,1)) -> 7457.52 | D10: =IF(B9=0,"",(B10-B9)/B9) -> 1.0346919 | E10: =IF(D10="","",IF(D10>0,"▲",IF(D10<0,"▼","▶"))) -> ▲
A11: =EDATE(A10,1) -> 45566 | B11: =SUMIFS(Data!$E$2:$E$201,Data!$H$2:$H$201,">="&A11,Data!$H$2:$H$201,"<"&EDATE(A11,1)) -> 14215.24 | C11: =SUMIFS(Data!$I$2:$I$201,Data!$H$2:$H$201,">="&A11,Data!$H$2:$H$201,"<"&EDATE(A11,1)) -> 4861.7 | D11: =IF(B10=0,"",(B11-B10)/B10) -> -0.30770497 | E11: =IF(D11="","",IF(D11>0,"▲",IF(D11<0,"▼","▶"))) -> ▼
A12: =EDATE(A11,1) -> 45597 | B12: =SUMIFS(Data!$E$2:$E$201,Data!$H$2:$H$201,">="&A12,Data!$H$2:$H$201,"<"&EDATE(A12,1)) -> 20135.03 | C12: =SUMIFS(Data!$I$2:$I$201,Data!$H$2:$H$201,">="&A12,Data!$H$2:$H$201,"<"&EDATE(A12,1)) -> 6814.88 | D12: =IF(B11=0,"",(B12-B11)/B11) -> 0.41643968 | E12: =IF(D12="","",IF(D12>0,"▲",IF(D12<0,"▼","▶"))) -> ▲
A13: =EDATE(A12,1) -> 45627 | B13: =SUMIFS(Data!$E$2:$E$201,Data!$H$2:$H$201,">="&A13,Data!$H$2:$H$201,"<"&EDATE(A13,1)) -> 11120.04 | C13: =SUMIFS(Data!$I$2:$I$201,Data!$H$2:$H$201,">="&A13,Data!$H$2:$H$201,"<"&EDATE(A13,1)) -> 3549.99 | D13: =IF(B12=0,"",(B13-B12)/B12) -> -0.44772667 | E13: =IF(D13="","",IF(D13>0,"▲",IF(D13<0,"▼","▶"))) -> ▼
A14: =EDATE(A13,1) -> 45658 | B14: =SUMIFS(Data!$E$2:$E$201,Data!$H$2:$H$201,">="&A14,Data!$H$2:$H$201,"<"&EDATE(A14,1)) -> 14914.65 | C14: =SUMIFS(Data!$I$2:$I$201,Data!$H$2:$H$201,">="&A14,Data!$H$2:$H$201,"<"&EDATE(A14,1)) -> 5763.4 | D14: =IF(B13=0,"",(B14-B13)/B13) -> 0.34124068 | E14: =IF(D14="","",IF(D14>0,"▲",IF(D14<0,"▼","▶"))) -> ▲
A15: =EDATE(A14,1) -> 45689 | B15: =SUMIFS(Data!$E$2:$E$201,Data!$H$2:$H$201,">="&A15,Data!$H$2:$H$201,"<"&EDATE(A15,1)) -> 14006.36 | C15: =SUMIFS(Data!$I$2:$I$201,Data!$H$2:$H$201,">="&A15,Data!$H$2:$H$201,"<"&EDATE(A15,1)) -> 5039.23 | D15: =IF(B14=0,"",(B15-B14)/B14) -> -0.060899183 | E15: =IF(D15="","",IF(D15>0,"▲",IF(D15<0,"▼","▶"))) -> ▼
A16: =EDATE(A15,1) -> 45717 | B16: =SUMIFS(Data!$E$2:$E$201,Data!$H$2:$H$201,">="&A16,Data!$H$2:$H$201,"<"&EDATE(A16,1)) -> 17655.22 | C16: =SUMIFS(Data!$I$2:$I$201,Data!$H$2:$H$201,">="&A16,Data!$H$2:$H$201,"<"&EDATE(A16,1)) -> 7071.39 | D16: =IF(B15=0,"",(B16-B15)/B15) -> 0.26051451 | E16: =IF(D16="","",IF(D16>0,"▲",IF(D16<0,"▼","▶"))) -> ▲
A17: =EDATE(A16,1) -> 45748 | B17: =SUMIFS(Data!$E$2:$E$201,Data!$H$2:$H$201,">="&A17,Data!$H$2:$H$201,"<"&EDATE(A17,1)) -> 3212.17 | C17: =SUMIFS(Data!$I$2:$I$201,Data!$H$2:$H$201,">="&A17,Data!$H$2:$H$201,"<"&EDATE(A17,1)) -> 1398.85 | D17: =IF(B16=0,"",(B17-B16)/B16) -> -0.81806117 | E17: =IF(D17="","",IF(D17>0,"▲",IF(D17<0,"▼","▶"))) -> ▼

Sheet High Value
A1: High-Value Customers - INDEX / MATCH
A2: Top 10 list pulled with INDEX+MATCH on Customers!Unique Rank. Also use the Tier filter on the Customers sheet.
A4: High-value customers (count): | C4: =COUNTIF(Customers!$H$5:$H$34,"High Value") -> 8
A5: Threshold used: | C5: =Customers!C3 -> 8300
A7: Rank | B7: Customer_ID | C7: Orders | D7: Total Purchase | E7: Total Profit | F7: Profit Margin | G7: Tier
A8: 1 | B8: =INDEX(Customers!$A$5:$A$34,MATCH($A8,Customers!$G$5:$G$34,0)) -> CUST015 | C8: =INDEX(Customers!$B$5:$B$34,MATCH($A8,Customers!$G$5:$G$34,0)) -> 11 | D8: =INDEX(Customers!$C$5:$C$34,MATCH($A8,Customers!$G$5:$G$34,0)) -> 11611.06 | E8: =INDEX(Customers!$D$5:$D$34,MATCH($A8,Customers!$G$5:$G$34,0)) -> 4201.59 | F8: =INDEX(Customers!$E$5:$E$34,MATCH($A8,Customers!$G$5:$G$34,0)) -> 0.36186102 | G8: =INDEX(Customers!$H$5:$H$34,MATCH($A8,Customers!$G$5:$G$34,0)) -> High Value
A9: 2 | B9: =INDEX(Customers!$A$5:$A$34,MATCH($A9,Customers!$G$5:$G$34,0)) -> CUST028 | C9: =INDEX(Customers!$B$5:$B$34,MATCH($A9,Customers!$G$5:$G$34,0)) -> 12 | D9: =INDEX(Customers!$C$5:$C$34,MATCH($A9,Customers!$G$5:$G$34,0)) -> 10293.87 | E9: =INDEX(Customers!$D$5:$D$34,MATCH($A9,Customers!$G$5:$G$34,0)) -> 3541.02 | F9: =INDEX(Customers!$E$5:$E$34,MATCH($A9,Customers!$G$5:$G$34,0)) -> 0.34399308 | G9: =INDEX(Customers!$H$5:$H$34,MATCH($A9,Customers!$G$5:$G$34,0)) -> High Value
A10: 3 | B10: =INDEX(Customers!$A$5:$A$34,MATCH($A10,Customers!$G$5:$G$34,0)) -> CUST007 | C10: =INDEX(Customers!$B$5:$B$34,MATCH($A10,Customers!$G$5:$G$34,0)) -> 10 | D10: =INDEX(Customers!$C$5:$C$34,MATCH($A10,Customers!$G$5:$G$34,0)) -> 9941.88 | E10: =INDEX(Customers!$D$5:$D$34,MATCH($A10,Customers!$G$5:$G$34,0)) -> 3936.26 | F10: =INDEX(Customers!$E$5:$E$34,MATCH($A10,Customers!$G$5:$G$34,0)) -> 0.39592713 | G10: =INDEX(Customers!$H$5:$H$34,MATCH($A10,Customers!$G$5:$G$34,0)) -> High Value
A11: 4 | B11: =INDEX(Customers!$A$5:$A$34,MATCH($A11,Customers!$G$5:$G$34,0)) -> CUST008 | C11: =INDEX(Customers!$B$5:$B$34,MATCH($A11,Customers!$G$5:$G$34,0)) -> 10 | D11: =INDEX(Customers!$C$5:$C$34,MATCH($A11,Customers!$G$5:$G$34,0)) -> 9760.8 | E11: =INDEX(Customers!$D$5:$D$34,MATCH($A11,Customers!$G$5:$G$34,0)) -> 3442.48 | F11: =INDEX(Customers!$E$5:$E$34,MATCH($A11,Customers!$G$5:$G$34,0)) -> 0.35268421 | G11: =INDEX(Customers!$H$5:$H$34,MATCH($A11,Customers!$G$5:$G$34,0)) -> High Value
A12: 5 | B12: =INDEX(Customers!$A$5:$A$34,MATCH($A12,Customers!$G$5:$G$34,0)) -> CUST026 | C12: =INDEX(Customers!$B$5:$B$34,MATCH($A12,Customers!$G$5:$G$34,0)) -> 9 | D12: =INDEX(Customers!$C$5:$C$34,MATCH($A12,Customers!$G$5:$G$34,0)) -> 9371.81 | E12: =INDEX(Customers!$D$5:$D$34,MATCH($A12,Customers!$G$5:$G$34,0)) -> 2922.02 | F12: =INDEX(Customers!$E$5:$E$34,MATCH($A12,Customers!$G$5:$G$34,0)) -> 0.31178822 | G12: =INDEX(Customers!$H$5:$H$34,MATCH($A12,Customers!$G$5:$G$34,0)) -> High Value
A13: 6 | B13: =INDEX(Customers!$A$5:$A$34,MATCH($A13,Customers!$G$5:$G$34,0)) -> CUST021 | C13: =INDEX(Customers!$B$5:$B$34,MATCH($A13,Customers!$G$5:$G$34,0)) -> 8 | D13: =INDEX(Customers!$C$5:$C$34,MATCH($A13,Customers!$G$5:$G$34,0)) -> 8740.18 | E13: =INDEX(Customers!$D$5:$D$34,MATCH($A13,Customers!$G$5:$G$34,0)) -> 2848.62 | F13: =INDEX(Customers!$E$5:$E$34,MATCH($A13,Customers!$G$5:$G$34,0)) -> 0.32592235 | G13: =INDEX(Customers!$H$5:$H$34,MATCH($A13,Customers!$G$5:$G$34,0)) -> High Value
A14: 7 | B14: =INDEX(Customers!$A$5:$A$34,MATCH($A14,Customers!$G$5:$G$34,0)) -> CUST003 | C14: =INDEX(Customers!$B$5:$B$34,MATCH($A14,Customers!$G$5:$G$34,0)) -> 9 | D14: =INDEX(Customers!$C$5:$C$34,MATCH($A14,Customers!$G$5:$G$34,0)) -> 8490.18 | E14: =INDEX(Customers!$D$5:$D$34,MATCH($A14,Customers!$G$5:$G$34,0)) -> 2652.75 | F14: =INDEX(Customers!$E$5:$E$34,MATCH($A14,Customers!$G$5:$G$34,0)) -> 0.31244921 | G14: =INDEX(Customers!$H$5:$H$34,MATCH($A14,Customers!$G$5:$G$34,0)) -> High Value
A15: 8 | B15: =INDEX(Customers!$A$5:$A$34,MATCH($A15,Customers!$G$5:$G$34,0)) -> CUST012 | C15: =INDEX(Customers!$B$5:$B$34,MATCH($A15,Customers!$G$5:$G$34,0)) -> 9 | D15: =INDEX(Customers!$C$5:$C$34,MATCH($A15,Customers!$G$5:$G$34,0)) -> 8339 | E15: =INDEX(Customers!$D$5:$D$34,MATCH($A15,Customers!$G$5:$G$34,0)) -> 2988.71 | F15: =INDEX(Customers!$E$5:$E$34,MATCH($A15,Customers!$G$5:$G$34,0)) -> 0.35840149 | G15: =INDEX(Customers!$H$5:$H$34,MATCH($A15,Customers!$G$5:$G$34,0)) -> High Value
A16: 9 | B16: =INDEX(Customers!$A$5:$A$34,MATCH($A16,Customers!$G$5:$G$34,0)) -> CUST030 | C16: =INDEX(Customers!$B$5:$B$34,MATCH($A16,Customers!$G$5:$G$34,0)) -> 9 | D16: =INDEX(Customers!$C$5:$C$34,MATCH($A16,Customers!$G$5:$G$34,0)) -> 7928.71 | E16: =INDEX(Customers!$D$5:$D$34,MATCH($A16,Customers!$G$5:$G$34,0)) -> 2965.48 | F16: =INDEX(Customers!$E$5:$E$34,MATCH($A16,Customers!$G$5:$G$34,0)) -> 0.37401797 | G16: =INDEX(Customers!$H$5:$H$34,MATCH($A16,Customers!$G$5:$G$34,0)) -> Standard
A17: 10 | B17: =INDEX(Customers!$A$5:$A$34,MATCH($A17,Customers!$G$5:$G$34,0)) -> CUST004 | C17: =INDEX(Customers!$B$5:$B$34,MATCH($A17,Customers!$G$5:$G$34,0)) -> 7 | D17: =INDEX(Customers!$C$5:$C$34,MATCH($A17,Customers!$G$5:$G$34,0)) -> 7813.59 | E17: =INDEX(Customers!$D$5:$D$34,MATCH($A17,Customers!$G$5:$G$34,0)) -> 3211.82 | F17: =INDEX(Customers!$E$5:$E$34,MATCH($A17,Customers!$G$5:$G$34,0)) -> 0.41105561 | G17: =INDEX(Customers!$H$5:$H$34,MATCH($A17,Customers!$G$5:$G$34,0)) -> Standard
A20: Customer lookup (pick an ID in the yellow cell)
A21: Customer_ID: | B21: CUST001
A22: Orders: | B22: =INDEX(Customers!$B$5:$B$34,MATCH($B$21,Customers!$A$5:$A$34,0)) -> 7
A23: Total Purchase: | B23: =INDEX(Customers!$C$5:$C$34,MATCH($B$21,Customers!$A$5:$A$34,0)) -> 6549.55
A24: Total Profit: | B24: =INDEX(Customers!$D$5:$D$34,MATCH($B$21,Customers!$A$5:$A$34,0)) -> 1868.77
A25: Rank: | B25: =INDEX(Customers!$F$5:$F$34,MATCH($B$21,Customers!$A$5:$A$34,0)) -> 15
A26: Tier: | B26: =INDEX(Customers!$H$5:$H$34,MATCH($B$21,Customers!$A$5:$A$34,0)) -> Standard

Sheet Pivot
A1: Pivot-style Summary: Total Sales by Region x Product Category
A2: Formula-based cross-tab (SUMIFS) so it always refreshes. For a real PivotTable see the Notes sheet.
A3: Total Sales
A4: Region | B4: Books | C4: Clothing | D4: Electronics | E4: Furniture | F4: Office Supplies | G4: Grand Total
A5: Central | B5: =SUMIFS(Data!$E$2:$E$201,Data!$C$2:$C$201,$A5,Data!$D$2:$D$201,B$4) -> 11297.15 | C5: =SUMIFS(Data!$E$2:$E$201,Data!$C$2:$C$201,$A5,Data!$D$2:$D$201,C$4) -> 12200.26 | D5: =SUMIFS(Data!$E$2:$E$201,Data!$C$2:$C$201,$A5,Data!$D$2:$D$201,D$4) -> 6621.24 | E5: =SUMIFS(Data!$E$2:$E$201,Data!$C$2:$C$201,$A5,Data!$D$2:$D$201,E$4) -> 4876.96 | F5: =SUMIFS(Data!$E$2:$E$201,Data!$C$2:$C$201,$A5,Data!$D$2:$D$201,F$4) -> 8472.72 | G5: =SUM(B5:F5) -> 43468.33
A6: East | B6: =SUMIFS(Data!$E$2:$E$201,Data!$C$2:$C$201,$A6,Data!$D$2:$D$201,B$4) -> 11389.09 | C6: =SUMIFS(Data!$E$2:$E$201,Data!$C$2:$C$201,$A6,Data!$D$2:$D$201,C$4) -> 2401.45 | D6: =SUMIFS(Data!$E$2:$E$201,Data!$C$2:$C$201,$A6,Data!$D$2:$D$201,D$4) -> 2869.54 | E6: =SUMIFS(Data!$E$2:$E$201,Data!$C$2:$C$201,$A6,Data!$D$2:$D$201,E$4) -> 7592.34 | F6: =SUMIFS(Data!$E$2:$E$201,Data!$C$2:$C$201,$A6,Data!$D$2:$D$201,F$4) -> 8189.22 | G6: =SUM(B6:F6) -> 32441.64
A7: North | B7: =SUMIFS(Data!$E$2:$E$201,Data!$C$2:$C$201,$A7,Data!$D$2:$D$201,B$4) -> 8037.01 | C7: =SUMIFS(Data!$E$2:$E$201,Data!$C$2:$C$201,$A7,Data!$D$2:$D$201,C$4) -> 8422.82 | D7: =SUMIFS(Data!$E$2:$E$201,Data!$C$2:$C$201,$A7,Data!$D$2:$D$201,D$4) -> 8191.71 | E7: =SUMIFS(Data!$E$2:$E$201,Data!$C$2:$C$201,$A7,Data!$D$2:$D$201,E$4) -> 6978.08 | F7: =SUMIFS(Data!$E$2:$E$201,Data!$C$2:$C$201,$A7,Data!$D$2:$D$201,F$4) -> 3345.8 | G7: =SUM(B7:F7) -> 34975.42
A8: South | B8: =SUMIFS(Data!$E$2:$E$201,Data!$C$2:$C$201,$A8,Data!$D$2:$D$201,B$4) -> 9588.04 | C8: =SUMIFS(Data!$E$2:$E$201,Data!$C$2:$C$201,$A8,Data!$D$2:$D$201,C$4) -> 8393.63 | D8: =SUMIFS(Data!$E$2:$E$201,Data!$C$2:$C$201,$A8,Data!$D$2:$D$201,D$4) -> 11989.07 | E8: =SUMIFS(Data!$E$2:$E$201,Data!$C$2:$C$201,$A8,Data!$D$2:$D$201,E$4) -> 7982.73 | F8: =SUMIFS(Data!$E$2:$E$201,Data!$C$2:$C$201,$A8,Data!$D$2:$D$201,F$4) -> 2295.32 | G8: =SUM(B8:F8) -> 40248.79
A9: West | B9: =SUMIFS(Data!$E$2:$E$201,Data!$C$2:$C$201,$A9,Data!$D$2:$D$201,B$4) -> 6691.17 | C9: =SUMIFS(Data!$E$2:$E$201,Data!$C$2:$C$201,$A9,Data!$D$2:$D$201,C$4) -> 10509.43 | D9: =SUMIFS(Data!$E$2:$E$201,Data!$C$2:$C$201,$A9,Data!$D$2:$D$201,D$4) -> 11372.44 | E9: =SUMIFS(Data!$E$2:$E$201,Data!$C$2:$C$201,$A9,Data!$D$2:$D$201,E$4) -> 9182.78 | F9: =SUMIFS(Data!$E$2:$E$201,Data!$C$2:$C$201,$A9,Data!$D$2:$D$201,F$4) -> 6327.76 | G9: =SUM(B9:F9) -> 44083.58
A10: Grand Total | B10: =SUM(B5:B9) -> 47002.46 | C10: =SUM(C5:C9) -> 41927.59 | D10: =SUM(D5:D9) -> 41044 | E10: =SUM(E5:E9) -> 36612.89 | F10: =SUM(F5:F9) -> 28630.82 | G10: =SUM(G5:G9) -> 195217.76
A12: Total Profit
A13: Region | B13: Books | C13: Clothing | D13: Electronics | E13: Furniture | F13: Office Supplies | G13: Grand Total
A14: Central | B14: =SUMIFS(Data!$I$2:$I$201,Data!$C$2:$C$201,$A14,Data!$D$2:$D$201,B$13) -> 4201.27 | C14: =SUMIFS(Data!$I$2:$I$201,Data!$C$2:$C$201,$A14,Data!$D$2:$D$201,C$13) -> 5395.6 | D14: =SUMIFS(Data!$I$2:$I$201,Data!$C$2:$C$201,$A14,Data!$D$2:$D$201,D$13) -> 1515.04 | E14: =SUMIFS(Data!$I$2:$I$201,Data!$C$2:$C$201,$A14,Data!$D$2:$D$201,E$13) -> 1566.46 | F14: =SUMIFS(Data!$I$2:$I$201,Data!$C$2:$C$201,$A14,Data!$D$2:$D$201,F$13) -> 3390.03 | G14: =SUM(B14:F14) -> 16068.4
A15: East | B15: =SUMIFS(Data!$I$2:$I$201,Data!$C$2:$C$201,$A15,Data!$D$2:$D$201,B$13) -> 4212.63 | C15: =SUMIFS(Data!$I$2:$I$201,Data!$C$2:$C$201,$A15,Data!$D$2:$D$201,C$13) -> 1025.15 | D15: =SUMIFS(Data!$I$2:$I$201,Data!$C$2:$C$201,$A15,Data!$D$2:$D$201,D$13) -> 662.68 | E15: =SUMIFS(Data!$I$2:$I$201,Data!$C$2:$C$201,$A15,Data!$D$2:$D$201,E$13) -> 2428.08 | F15: =SUMIFS(Data!$I$2:$I$201,Data!$C$2:$C$201,$A15,Data!$D$2:$D$201,F$13) -> 3310.05 | G15: =SUM(B15:F15) -> 11638.59
A16: North | B16: =SUMIFS(Data!$I$2:$I$201,Data!$C$2:$C$201,$A16,Data!$D$2:$D$201,B$13) -> 2778.44 | C16: =SUMIFS(Data!$I$2:$I$201,Data!$C$2:$C$201,$A16,Data!$D$2:$D$201,C$13) -> 3691.09 | D16: =SUMIFS(Data!$I$2:$I$201,Data!$C$2:$C$201,$A16,Data!$D$2:$D$201,D$13) -> 1783.05 | E16: =SUMIFS(Data!$I$2:$I$201,Data!$C$2:$C$201,$A16,Data!$D$2:$D$201,E$13) -> 2217.72 | F16: =SUMIFS(Data!$I$2:$I$201,Data!$C$2:$C$201,$A16,Data!$D$2:$D$201,F$13) -> 1431.98 | G16: =SUM(B16:F16) -> 11902.28
A17: South | B17: =SUMIFS(Data!$I$2:$I$201,Data!$C$2:$C$201,$A17,Data!$D$2:$D$201,B$13) -> 3416.81 | C17: =SUMIFS(Data!$I$2:$I$201,Data!$C$2:$C$201,$A17,Data!$D$2:$D$201,C$13) -> 3944.21 | D17: =SUMIFS(Data!$I$2:$I$201,Data!$C$2:$C$201,$A17,Data!$D$2:$D$201,D$13) -> 2783.44 | E17: =SUMIFS(Data!$I$2:$I$201,Data!$C$2:$C$201,$A17,Data!$D$2:$D$201,E$13) -> 2540.36 | F17: =SUMIFS(Data!$I$2:$I$201,Data!$C$2:$C$201,$A17,Data!$D$2:$D$201,F$13) -> 1007.09 | G17: =SUM(B17:F17) -> 13691.91
A18: West | B18: =SUMIFS(Data!$I$2:$I$201,Data!$C$2:$C$201,$A18,Data!$D$2:$D$201,B$13) -> 2292.48 | C18: =SUMIFS(Data!$I$2:$I$201,Data!$C$2:$C$201,$A18,Data!$D$2:$D$201,C$13) -> 4728.44 | D18: =SUMIFS(Data!$I$2:$I$201,Data!$C$2:$C$201,$A18,Data!$D$2:$D$201,D$13) -> 2437.94 | E18: =SUMIFS(Data!$I$2:$I$201,Data!$C$2:$C$201,$A18,Data!$D$2:$D$201,E$13) -> 2826.52 | F18: =SUMIFS(Data!$I$2:$I$201,Data!$C$2:$C$201,$A18,Data!$D$2:$D$201,F$13) -> 2700.45 | G18: =SUM(B18:F18) -> 14985.83
A19: Grand Total | B19: =SUM(B14:B18) -> 16901.63 | C19: =SUM(C14:C18) -> 18784.49 | D19: =SUM(D14:D18) -> 9182.15 | E19: =SUM(E14:E18) -> 11579.14 | F19: =SUM(F14:F18) -> 11839.6 | G19: =SUM(G14:G18) -> 68287.01

Sheet Dashboard
A1: SALES DASHBOARD
A3: Total Sales | B3: Total Profit | C3: Profit Margin | D3: Avg Discount | E3: Customers | F3: High-Value Customers
A4: =SUM(Data!$E$2:$E$201) -> 195217.76 | B4: =SUM(Data!$I$2:$I$201) -> 68287.01 | C4: =SUM(Data!$I$2:$I$201)/SUM(Data!$E$2:$E$201) -> 0.34979917 | D4: =AVERAGE(Data!$G$2:$G$201) -> 0.09725 | E4: =COUNTA(Customers!$A$5:$A$34) -> 30 | F4: ='High Value'!C4 -> 8
A6: Top Customer | B6: Best Region | C6: Best Product | D6: Last Full-Month Growth | E6: Avg Order Value | F6: Profit vs Sales R²
A7: =INDEX(Customers!$A$5:$A$34,MATCH(1,Customers!$G$5:$G$34,0)) -> CUST015 | B7: =INDEX(Pivot!$A$5:$A$9,MATCH(MAX(Pivot!$G$5:$G$9),Pivot!$G$5:$G$9,0)) -> West | C7: =INDEX(Pivot!$B$4:$F$4,MATCH(MAX(Pivot!$B$10:$F$10),Pivot!$B$10:$F$10,0)) -> Books | D7: ='Monthly Growth'!E16&" "&TEXT('Monthly Growth'!D16,"0.0%") -> ▲ 26.1% | E7: =AVERAGE(Data!$E$2:$E$201) -> 976.0888 | F7: =Regression!B6 -> 0.5981523
A10: KEY INSIGHTS
A11: ="1. "&B7&" is the strongest region with "&TEXT(MAX(Pivot!$G$5:$G$9),"#,##0")&" in sales ("&TEXT(MAX(Pivot!$G$5:$G$9)/Pivot!$G$10,"0%")&" of total)." -> 1. West is the strongest region with 44,084 in sales (23% of total).
A12: ="2. "&C7&" is the top product category, contributing "&TEXT(MAX(Pivot!$B$10:$F$10)/Pivot!$G$10,"0%")&" of sales." -> 2. Books is the top product category, contributing 24% of sales.
A13: ="3. Top customer "&A7&" spent "&TEXT(MAX(Customers!$C$5:$C$34),"#,##0")&"; "&F4&" customers are above the high-value threshold." -> 3. Top customer CUST015 spent 11,611; 8 customers are above the high-value threshold.
A14: ="4. Overall profit margin is "&TEXT(C4,"0.0%")&" with an average discount of "&TEXT(D4,"0.0%")&"." -> 4. Overall profit margin is 35.0% with an average discount of 9.7%.
A15: ="5. Last full month (Mar-2025) sales moved "&D7&" versus the previous month." -> 5. Last full month (Mar-2025) sales moved ▲ 26.1% versus the previous month.
A16: =IF(Regression!F13<0.05,"6. Sales significantly drives profit (regression p-value < 0.05, R² = "&TEXT(Regression!B6,"0.00")&").","6. Sales does not significantly explain profit (p-value >= 0.05).") -> 6. Sales significantly drives profit (regression p-value < 0.05, R² = 0.60).

Sheet Descriptive Stats
A1: Descriptive Statistics
A2: Same output as Data Analysis ToolPak > Descriptive Statistics (Summary statistics), via live formulas.
A4: Statistic | B4: Sales | C4: Quantity | D4: Discount | E4: Profit | F4: Gross Sales | G4: Cost
A5: Mean | B5: =AVERAGE(Data!$E$2:$E$201) -> 976.0888 | C5: =AVERAGE(Data!$F$2:$F$201) -> 9.995 | D5: =AVERAGE(Data!$G$2:$G$201) -> 0.09725 | E5: =AVERAGE(Data!$I$2:$I$201) -> 341.43505 | F5: =AVERAGE(Data!$J$2:$J$201) -> 1090.136 | G5: =AVERAGE(Data!$K$2:$K$201) -> 634.65375
A6: Standard Error | B6: =STDEV(Data!$E$2:$E$201)/SQRT(COUNT(Data!$E$2:$E$201)) -> 21.16185 | C6: =STDEV(Data!$F$2:$F$201)/SQRT(COUNT(Data!$F$2:$F$201)) -> 0.39927683 | D6: =STDEV(Data!$G$2:$G$201)/SQRT(COUNT(Data!$G$2:$G$201)) -> 0.0051142414 | E6: =STDEV(Data!$I$2:$I$201)/SQRT(COUNT(Data!$I$2:$I$201)) -> 9.6001196 | F6: =STDEV(Data!$J$2:$J$201)/SQRT(COUNT(Data!$J$2:$J$201)) -> 25.31705 | G6: =STDEV(Data!$K$2:$K$201)/SQRT(COUNT(Data!$K$2:$K$201)) -> 15.02474
A7: Median | B7: =MEDIAN(Data!$E$2:$E$201) -> 976.72 | C7: =MEDIAN(Data!$F$2:$F$201) -> 10 | D7: =MEDIAN(Data!$G$2:$G$201) -> 0.1 | E7: =MEDIAN(Data!$I$2:$I$201) -> 332.255 | F7: =MEDIAN(Data!$J$2:$J$201) -> 1074.5947 | G7: =MEDIAN(Data!$K$2:$K$201) -> 630.855
A8: Mode | B8: =IFERROR(MODE(Data!$E$2:$E$201),"N/A") -> N/A | C8: =IFERROR(MODE(Data!$F$2:$F$201),"N/A") -> 8 | D8: =IFERROR(MODE(Data!$G$2:$G$201),"N/A") -> 0.2 | E8: =IFERROR(MODE(Data!$I$2:$I$201),"N/A") -> N/A | F8: =IFERROR(MODE(Data!$J$2:$J$201),"N/A") -> N/A | G8: =IFERROR(MODE(Data!$K$2:$K$201),"N/A") -> N/A
A9: Standard Deviation | B9: =STDEV(Data!$E$2:$E$201) -> 299.27376 | C9: =STDEV(Data!$F$2:$F$201) -> 5.646627 | D9: =STDEV(Data!$G$2:$G$201) -> 0.072326295 | E9: =STDEV(Data!$I$2:$I$201) -> 135.76619 | F9: =STDEV(Data!$J$2:$J$201) -> 358.03715 | G9: =STDEV(Data!$K$2:$K$201) -> 212.48191
A10: Sample Variance | B10: =VAR(Data!$E$2:$E$201) -> 89564.783 | C10: =VAR(Data!$F$2:$F$201) -> 31.884397 | D10: =VAR(Data!$G$2:$G$201) -> 0.005231093 | E10: =VAR(Data!$I$2:$I$201) -> 18432.459 | F10: =VAR(Data!$J$2:$J$201) -> 128190.6 | G10: =VAR(Data!$K$2:$K$201) -> 45148.562
A11: Kurtosis | B11: =KURT(Data!$E$2:$E$201) -> -0.088595232 | C11: =KURT(Data!$F$2:$F$201) -> -1.2091054 | D11: =KURT(Data!$G$2:$G$201) -> -1.3257012 | E11: =KURT(Data!$I$2:$I$201) -> 0.26450644 | F11: =KURT(Data!$J$2:$J$201) -> 0.6466503 | G11: =KURT(Data!$K$2:$K$201) -> 0.34253245
A12: Skewness | B12: =SKEW(Data!$E$2:$E$201) -> 0.14685797 | C12: =SKEW(Data!$F$2:$F$201) -> 0.060845864 | D12: =SKEW(Data!$G$2:$G$201) -> 0.096827386 | E12: =SKEW(Data!$I$2:$I$201) -> 0.57339636 | F12: =SKEW(Data!$J$2:$J$201) -> 0.48728209 | G12: =SKEW(Data!$K$2:$K$201) -> 0.41723036
A13: Range | B13: =MAX(Data!$E$2:$E$201)-MIN(Data!$E$2:$E$201) -> 1665.15 | C13: =MAX(Data!$F$2:$F$201)-MIN(Data!$F$2:$F$201) -> 18 | D13: =MAX(Data!$G$2:$G$201)-MIN(Data!$G$2:$G$201) -> 0.2 | E13: =MAX(Data!$I$2:$I$201)-MIN(Data!$I$2:$I$201) -> 704.83 | F13: =MAX(Data!$J$2:$J$201)-MIN(Data!$J$2:$J$201) -> 2146.065 | G13: =MAX(Data!$K$2:$K$201)-MIN(Data!$K$2:$K$201) -> 1151.09
A14: Minimum | B14: =MIN(Data!$E$2:$E$201) -> 258.51 | C14: =MIN(Data!$F$2:$F$201) -> 1 | D14: =MIN(Data!$G$2:$G$201) -> 0 | E14: =MIN(Data!$I$2:$I$201) -> 64.63 | F14: =MIN(Data!$J$2:$J$201) -> 258.51 | G14: =MIN(Data!$K$2:$K$201) -> 193.88
A15: Maximum | B15: =MAX(Data!$E$2:$E$201) -> 1923.66 | C15: =MAX(Data!$F$2:$F$201) -> 19 | D15: =MAX(Data!$G$2:$G$201) -> 0.2 | E15: =MAX(Data!$I$2:$I$201) -> 769.46 | F15: =MAX(Data!$J$2:$J$201) -> 2404.575 | G15: =MAX(Data!$K$2:$K$201) -> 1344.97
A16: Sum | B16: =SUM(Data!$E$2:$E$201) -> 195217.76 | C16: =SUM(Data!$F$2:$F$201) -> 1999 | D16: =SUM(Data!$G$2:$G$201) -> 19.45 | E16: =SUM(Data!$I$2:$I$201) -> 68287.01 | F16: =SUM(Data!$J$2:$J$201) -> 218027.19 | G16: =SUM(Data!$K$2:$K$201) -> 126930.75
A17: Count | B17: =COUNT(Data!$E$2:$E$201) -> 200 | C17: =COUNT(Data!$F$2:$F$201) -> 200 | D17: =COUNT(Data!$G$2:$G$201) -> 200 | E17: =COUNT(Data!$I$2:$I$201) -> 200 | F17: =COUNT(Data!$J$2:$J$201) -> 200 | G17: =COUNT(Data!$K$2:$K$201) -> 200
